RTL/mem.sv
//===========================================================
// picoCPU Project
//-----------------------------------------------------------
// File Name   : mem.sv
// Description : Memory and Port
//-----------------------------------------------------------
// History :
// Rev.01 2026.02.02 M.Maruyama First Release
//-----------------------------------------------------------
// Copyright (C) 2026 M.Maruyama
//===========================================================

//-------------------------------------------------
// CPU Instruction
//-------------------------------------------------
// 00iiiiii  ADD #imm6    A<--A+#imm6
// 01aaaaaa  JNZ @addr6   if (A!=0) PC<--addr6
// 10aaaaaa  LDA @addr6   A<--@addr6
// 11aaaaaa  STA @addr6   @addr6<--A

//-------------------------------------------------
// Example Program blinkLED
//-------------------------------------------------
// ADDR CODE MNEMONIC
// 0x00 0xbe START   LDA  @PORTI
// 0x01 0x40         JNZ  @START
// 0x02 0xa1 INIT    LDA  @TEN
// 0x03 0x3f LOOP    ADD  #-1
// 0x04 0x43         JNZ  @LOOP
// 0x05 0xbf OUT     LDA  @POUT
// 0x06 0x01         ADD  #1
// 0x07 0xff         STA  @POUT
// 0x08 0xa0 RESTART LDA  @ONE
// 0x09 0x40         JNZ  @START
//
// 0x20 0x01 ONE     CONST 0x01
// 0x21 0x0a TEN     CONST 0X0a
//
// 0x3e 0x00 PORTI   DATA   0x00
// 0x3f 0x00 PORTO   DATA   0x00 

//========================================
// Memory with Port I/O
//========================================
module MEM
(
    input  logic CLK,
    input  logic RES,
    //
    input  logic [5:0] ADDR,
    input  logic       RE,
    input  logic       WE,
    input  logic [7:0] WDATA,
    output logic [7:0] RDATA,
    //
    input  logic [7:0] PORTI,
    output logic [7:0] PORTO
);

// Memory Mat
logic [7:0] mem[0:63];

// Initialize Memory
initial
begin
    mem[ 0]=8'hbe; mem[ 1]=8'h40; mem[ 2]=8'ha1; mem[ 3]=8'h3f; 
    mem[ 4]=8'h43; mem[ 5]=8'hbf; mem[ 6]=8'h01; mem[ 7]=8'hff; 
    mem[ 8]=8'ha0; mem[ 9]=8'h40;
    mem[32]=9'h01; mem[33]=8'h0a;
end

// Read Operation
always_ff @(posedge CLK, posedge RES)
begin
    if (RES)
        RDATA <= 8'h00;
    else if (RE & (ADDR == 6'h3e))
        RDATA <= PORTI;      // PORT Input
    else if (RE & (ADDR == 6'h3f))
        RDATA <= PORTO;      // PORT Output
    else if (RE)
        RDATA <= mem[ADDR];  // Memory
end

// Write Operation
always_ff @(posedge CLK)
begin
    if (WE) mem[ADDR] <= WDATA; // Memory
end
//
always_ff @(posedge CLK, posedge RES)
begin
    if (RES)
        PORTO <= 8'h00;
    else if (WE & (ADDR == 6'h3f))
        PORTO <= WDATA;        // Port Output
end

endmodule
//===========================================================
// End of File
//===========================================================

RTL/cpu.sv
//===========================================================
// picoCPU Project
//-----------------------------------------------------------
// File Name   : cpu.sv
// Description : CPU Core
//-----------------------------------------------------------
// History :
// Rev.01 2026.02.02 M.Maruyama First Release
//-----------------------------------------------------------
// Copyright (C) 2026 M.Maruyama
//===========================================================

//-------------------------------------------------
// CPU Instruction
//-------------------------------------------------
// 00iiiiii  ADD #imm6    A<--A+#imm6
// 01aaaaaa  JNZ @addr6   if (A!=0) PC<--addr6
// 10aaaaaa  LDA @addr6   A<--@addr6
// 11aaaaaa  STA @addr6   @addr6<--A

//------------------------------
// Cotrol State
//------------------------------
`define STATE_INIT   3'h0
`define STATE_FETCH  3'h1
`define STATE_DECODE 3'h2
`define STATE_ADD    3'h3
`define STATE_JNZ    3'h4
`define STATE_LDA    3'h5
`define STATE_LDA2   3'h6
`define STATE_STA    3'h7

//========================================
// CPU
//========================================
module CPU
(
    input  logic CLK,
    input  logic RES,
    //
    output logic [5:0] ADDR,
    output logic       RE,
    output logic       WE,
    output logic [7:0] WDATA,
    input  logic [7:0] RDATA
);

//------------------------------------
// CPU Data Path : Instruction Code
//------------------------------------
logic [7:0] icode;     // Instruction Code
logic       icode_get; // Get icode
logic [1:0] opcode;    // Operation Code
//
assign opcode = RDATA[7:6];
//
always_ff @(posedge CLK, posedge RES)
begin
    if (RES)
        icode <= 8'h00;
    else if (icode_get)
        icode <= RDATA;
end

//------------------------------------
// CPU Data Path : Program Counter
//------------------------------------
logic [5:0] pc;      // Program Counter
logic [5:0] pc_next; // Next PC
logic       pc_inc;  // Increment PC
logic       pc_jmp;  // Jump PC
//
assign pc_next = icode[5:0];
//
always_ff @(posedge CLK, posedge RES)
begin
    if (RES)
        pc <= 6'h00;
    else if (pc_inc)
        pc <= pc + 6'h01;
    else if (pc_jmp)
        pc <= pc_next;
end

//------------------------------------
// CPU Data Path : Register A
//------------------------------------
logic [7:0] regA;     // Register A
logic       regA_ld;  // Load to A
logic       regA_add; // Add to A
logic       regA_nz;  // A is Not Zero
logic [7:0] imm;      // Immediate Data
//
assign imm = {icode[5], icode[5], icode[5:0]};
//
always_ff @(posedge CLK, posedge RES)
begin
    if (RES)
        regA <= 8'h00;
    else if (regA_ld)
        regA <= RDATA;
    else if (regA_add)
        regA <= regA + imm;
end
//
assign regA_nz = |regA;

//------------------------------------
// CPU Data Parh : Memory Access
//------------------------------------
logic addr_pc;
logic addr_rw;
//
assign ADDR = (addr_pc)? pc
            : (addr_rw)? icode[5:0]
            : 6'h00;
assign WDATA = regA;

//------------------------------------
// CPU Control Logic
//------------------------------------
logic [2:0] state;
logic [2:0] state_next;
//
always_ff @(posedge CLK, posedge RES)
begin
    if (RES)
        state <= `STATE_INIT;
    else
        state <= state_next;
end
//
always_comb
begin
    // Set Default Value
    icode_get = 1'b0;
    pc_inc    = 1'b0;
    pc_jmp    = 1'b0;
    regA_ld   = 1'b0;
    regA_add  = 1'b0;
    addr_pc   = 1'b0;
    addr_rw   = 1'b0;
    RE        = 1'b0;
    WE        = 1'b0;
    //
    case (state)
        //---------------------------------
        // Initial State
        `STATE_INIT:
        begin
            state_next = `STATE_FETCH;        
        end
        //---------------------------------
        // Instruction Fetch
        `STATE_FETCH:
        begin
            RE = 1'b1;
            addr_pc = 1'b1;
            state_next = `STATE_DECODE;
        end
        //---------------------------------
        // Instruction Decode
        `STATE_DECODE:
        begin
            icode_get = 1'b1;
                 if (opcode == 2'b00) state_next = `STATE_ADD;
            else if (opcode == 2'b01) state_next = `STATE_JNZ;
            else if (opcode == 2'b10) state_next = `STATE_LDA;
            else if (opcode == 2'b11) state_next = `STATE_STA;
            else state_next = `STATE_INIT; // never reach here
        end
        //---------------------------------
        // ADD
        `STATE_ADD:
        begin
            regA_add = 1'b1;
            pc_inc   = 1'b1;
            state_next = `STATE_FETCH;
        end
        //---------------------------------
        // JNZ
        `STATE_JNZ:
        begin
            pc_jmp =  regA_nz;
            pc_inc = ~regA_nz;
            state_next = `STATE_FETCH;
        end
        //---------------------------------
        // LDA
        `STATE_LDA:
        begin
            RE = 1'b1;
            addr_rw = 1'b1;
            state_next = `STATE_LDA2;
        end
        `STATE_LDA2:
        begin
            regA_ld = 1'b1;
            pc_inc   = 1'b1;
            state_next = `STATE_FETCH;
        end
        //---------------------------------
        // STA
        `STATE_STA:
        begin
            WE = 1'b1;
            addr_rw = 1'b1;
            pc_inc   = 1'b1;
            state_next = `STATE_FETCH;        
        end
        //---------------------------------
        // Default (NOP)
        default:
        begin
            pc_inc   = 1'b1;
            state_next = `STATE_FETCH;                
        end
    endcase
end

endmodule
//===========================================================
// End of File
//===========================================================

RTL/top.sv
//===========================================================
// picoCPU Project
//-----------------------------------------------------------
// File Name   : top.sv
// Description : Top Layer
//-----------------------------------------------------------
// History :
// Rev.01 2026.02.02 M.Maruyama First Release
//-----------------------------------------------------------
// Copyright (C) 2026 M.Maruyama
//===========================================================


//========================================
// TOP
//========================================
module TOP
(
    input  logic CLK,
    input  logic RES,
    //
    input  logic [7:0] PORTI,
    output logic [7:0] PORTO
);

//-------------------------------
// Internal Signals
//-------------------------------
logic [5:0] addr;
logic       re;
logic       we;
logic [7:0] wdata;
logic [7:0] rdata;
    
//-------------------------------
// CPU
//-------------------------------
CPU U_CPU
(
    .CLK (CLK),
    .RES (RES),
    //
    .ADDR  (addr),
    .RE    (re),
    .WE    (we),
    .WDATA (wdata),
    .RDATA (rdata)
);

//-------------------------------
// Memory and Port
//-------------------------------
MEM U_MEM
(
    .CLK (CLK),
    .RES (RES),
    //
    .ADDR  (addr),
    .RE    (re),
    .WE    (we),
    .WDATA (wdata),
    .RDATA (rdata),
    //
    .PORTI (PORTI),
    .PORTO (PORTO)
);

endmodule
//===========================================================
// End of File
//===========================================================

SIM/tb.sv
//===========================================================
// picoCPU Project
//-----------------------------------------------------------
// File Name   : tb.sv
// Description : Testbench for picoCPU System
//-----------------------------------------------------------
// History :
// Rev.01 2026.02.02 M.Maruyama First Release
//-----------------------------------------------------------
// Copyright (C) 2026 M.Maruyama
//===========================================================

`timescale 1ns/10ps

`define TB_CYCLE           100 //ns
`define TB_FINISH_COUNT  10000 //cyc

//------------------
// Top of Test Bench
//------------------
module tb();

//-----------------------------
// Generate Wave File to Check
//-----------------------------
initial
begin
    $dumpfile("tb.vcd");
    $dumpvars(0, tb);
end

//-------------------------------
// Generate Clock
//-------------------------------
logic clk;
//
initial clk = 1'b0;
always #(`TB_CYCLE / 2) clk = ~clk;

//--------------------------
// Generate Reset
//--------------------------
logic res;
//
initial
begin
    res = 1'b1;
        # (`TB_CYCLE * 10)
    res = 1'b0;       
end

//----------------------
// Cycle Counter
//----------------------
logic [31:0] tb_cycle_counter;
//
always_ff @(posedge clk, posedge res)
begin
    if (res)
        tb_cycle_counter <= 32'h0;
    else
        tb_cycle_counter <= tb_cycle_counter + 32'h1;
end
//
initial
begin
    forever
    begin
        @(posedge clk);
        if (tb_cycle_counter == `TB_FINISH_COUNT)
        begin
            $display("***** SIMULATION TIMEOUT ***** at %d", tb_cycle_counter);
            $finish;
        end
    end
end


//---------------------
// DUT Top
//---------------------
logic [7:0] porti;
logic [7:0] porto;
//
TOP U_TOP
(
    .CLK    (clk),
    .RES    (res),
    //
    .PORTI  (porti),
    .PORTO  (porto)
);

//--------------------------
// Input Pattern (Stimulus)
//--------------------------
initial
begin
    // Wait for Reset Release
    porti = 8'hff;
    @(posedge clk);
    @(negedge res);
    @(posedge clk);
    // Start
    #(`TB_CYCLE * 100);
    porti = 8'h00;
    #(`TB_CYCLE * 500);
    porti = 8'hff;
    #(`TB_CYCLE * 100);
    porti = 8'h00;
    #(`TB_CYCLE * 500);
    // End of Stimulus
    $finish;
end

endmodule
//===========================================================
// End of File
//===========================================================

SIM/tb.vcd
$date
	Tue Feb  3 23:00:09 2026
$end
$version
	Icarus Verilog
$end
$timescale
	10ps
$end
$scope module tb $end
$var wire 8 ! porto [7:0] $end
$var reg 1 " clk $end
$var reg 8 # porti [7:0] $end
$var reg 1 $ res $end
$var reg 32 % tb_cycle_counter [31:0] $end
$scope module U_TOP $end
$var wire 1 " CLK $end
$var wire 8 & PORTI [7:0] $end
$var wire 1 $ RES $end
$var wire 1 ' we $end
$var wire 8 ( wdata [7:0] $end
$var wire 1 ) re $end
$var wire 8 * rdata [7:0] $end
$var wire 6 + addr [5:0] $end
$var wire 8 , PORTO [7:0] $end
$scope module U_CPU $end
$var wire 1 " CLK $end
$var wire 1 $ RES $end
$var wire 8 - WDATA [7:0] $end
$var wire 1 . regA_nz $end
$var wire 6 / pc_next [5:0] $end
$var wire 2 0 opcode [1:0] $end
$var wire 8 1 imm [7:0] $end
$var wire 8 2 RDATA [7:0] $end
$var wire 6 3 ADDR [5:0] $end
$var reg 1 ) RE $end
$var reg 1 ' WE $end
$var reg 1 4 addr_pc $end
$var reg 1 5 addr_rw $end
$var reg 8 6 icode [7:0] $end
$var reg 1 7 icode_get $end
$var reg 6 8 pc [5:0] $end
$var reg 1 9 pc_inc $end
$var reg 1 : pc_jmp $end
$var reg 8 ; regA [7:0] $end
$var reg 1 < regA_add $end
$var reg 1 = regA_ld $end
$var reg 3 > state [2:0] $end
$var reg 3 ? state_next [2:0] $end
$upscope $end
$scope module U_MEM $end
$var wire 6 @ ADDR [5:0] $end
$var wire 1 " CLK $end
$var wire 8 A PORTI [7:0] $end
$var wire 1 ) RE $end
$var wire 1 $ RES $end
$var wire 8 B WDATA [7:0] $end
$var wire 1 ' WE $end
$var reg 8 C PORTO [7:0] $end
$var reg 8 D RDATA [7:0] $end
$upscope $end
$upscope $end
$upscope $end
$enddefinitions $end
$comment Show the parameter values. $end
$dumpall
$end
#0
$dumpvars
b0 D
b0 C
b0 B
b11111111 A
b0 @
b1 ?
b0 >
0=
0<
b0 ;
0:
09
b0 8
07
b0 6
05
04
b0 3
b0 2
b0 1
b0 0
b0 /
0.
b0 -
b0 ,
b0 +
b0 *
0)
b0 (
0'
b11111111 &
bx %
1$
b11111111 #
0"
b0 !
$end
#5000
b0 %
1"
#10000
0"
#15000
1"
#20000
0"
#25000
1"
#30000
0"
#35000
1"
#40000
0"
#45000
1"
#50000
0"
#55000
1"
#60000
0"
#65000
1"
#70000
0"
#75000
1"
#80000
0"
#85000
1"
#90000
0"
#95000
1"
#100000
0"
0$
#105000
b10 ?
14
1)
b1 %
b1 >
1"
#110000
0"
#115000
b101 ?
17
0)
04
b10 0
b10 >
b10111110 *
b10111110 2
b10111110 D
b10 %
1"
#120000
0"
#125000
b111110 +
b111110 3
b111110 @
b110 ?
15
1)
07
b111110 /
b11111110 1
b11 %
b101 >
b10111110 6
1"
#130000
0"
#135000
b0 +
b0 3
b0 @
b1 ?
19
1=
0)
05
b11 0
b110 >
b11111111 *
b11111111 2
b11111111 D
b100 %
1"
#140000
0"
#145000
b1 +
b1 3
b1 @
b10 ?
14
1)
0=
09
b101 %
b1 >
1.
b11111111 (
b11111111 -
b11111111 B
b11111111 ;
b1 8
1"
#150000
0"
#155000
b0 +
b0 3
b0 @
b100 ?
17
0)
04
b1 0
b10 >
b1000000 *
b1000000 2
b1000000 D
b110 %
1"
#160000
0"
#165000
b1 ?
1:
07
b0 /
b0 1
b111 %
b100 >
b1000000 6
1"
#170000
0"
#175000
b10 ?
14
1)
0:
b0 8
b1 >
b1000 %
1"
#180000
0"
#185000
b10 0
b101 ?
17
0)
04
b1001 %
b10111110 *
b10111110 2
b10111110 D
b10 >
1"
#190000
0"
#195000
b111110 +
b111110 3
b111110 @
b111110 /
b11111110 1
b110 ?
15
1)
07
b10111110 6
b101 >
b1010 %
1"
#200000
0"
#205000
b0 +
b0 3
b0 @
b11 0
b1 ?
19
1=
0)
05
b1011 %
b11111111 *
b11111111 2
b11111111 D
b110 >
1"
#210000
0"
#215000
b1 +
b1 3
b1 @
b10 ?
14
1)
0=
09
b1 8
b1 >
b1100 %
1"
#220000
0"
#225000
b0 +
b0 3
b0 @
b1 0
b100 ?
17
0)
04
b1101 %
b1000000 *
b1000000 2
b1000000 D
b10 >
1"
#230000
0"
#235000
b0 /
b0 1
b1 ?
1:
07
b1000000 6
b100 >
b1110 %
1"
#240000
0"
#245000
b10 ?
14
1)
0:
b1111 %
b1 >
b0 8
1"
#250000
0"
#255000
b101 ?
17
0)
04
b10 0
b10 >
b10111110 *
b10111110 2
b10111110 D
b10000 %
1"
#260000
0"
#265000
b111110 +
b111110 3
b111110 @
b110 ?
15
1)
07
b111110 /
b11111110 1
b10001 %
b101 >
b10111110 6
1"
#270000
0"
#275000
b0 +
b0 3
b0 @
b1 ?
19
1=
0)
05
b11 0
b110 >
b11111111 *
b11111111 2
b11111111 D
b10010 %
1"
#280000
0"
#285000
b1 +
b1 3
b1 @
b10 ?
14
1)
0=
09
b10011 %
b1 >
b1 8
1"
#290000
0"
#295000
b0 +
b0 3
b0 @
b100 ?
17
0)
04
b1 0
b10 >
b1000000 *
b1000000 2
b1000000 D
b10100 %
1"
#300000
0"
#305000
b1 ?
1:
07
b0 /
b0 1
b10101 %
b100 >
b1000000 6
1"
#310000
0"
#315000
b10 ?
14
1)
0:
b0 8
b1 >
b10110 %
1"
#320000
0"
#325000
b10 0
b101 ?
17
0)
04
b10111 %
b10111110 *
b10111110 2
b10111110 D
b10 >
1"
#330000
0"
#335000
b111110 +
b111110 3
b111110 @
b111110 /
b11111110 1
b110 ?
15
1)
07
b10111110 6
b101 >
b11000 %
1"
#340000
0"
#345000
b0 +
b0 3
b0 @
b11 0
b1 ?
19
1=
0)
05
b11001 %
b11111111 *
b11111111 2
b11111111 D
b110 >
1"
#350000
0"
#355000
b1 +
b1 3
b1 @
b10 ?
14
1)
0=
09
b1 8
b1 >
b11010 %
1"
#360000
0"
#365000
b0 +
b0 3
b0 @
b1 0
b100 ?
17
0)
04
b11011 %
b1000000 *
b1000000 2
b1000000 D
b10 >
1"
#370000
0"
#375000
b0 /
b0 1
b1 ?
1:
07
b1000000 6
b100 >
b11100 %
1"
#380000
0"
#385000
b10 ?
14
1)
0:
b11101 %
b1 >
b0 8
1"
#390000
0"
#395000
b101 ?
17
0)
04
b10 0
b10 >
b10111110 *
b10111110 2
b10111110 D
b11110 %
1"
#400000
0"
#405000
b111110 +
b111110 3
b111110 @
b110 ?
15
1)
07
b111110 /
b11111110 1
b11111 %
b101 >
b10111110 6
1"
#410000
0"
#415000
b0 +
b0 3
b0 @
b1 ?
19
1=
0)
05
b11 0
b110 >
b11111111 *
b11111111 2
b11111111 D
b100000 %
1"
#420000
0"
#425000
b1 +
b1 3
b1 @
b10 ?
14
1)
0=
09
b100001 %
b1 >
b1 8
1"
#430000
0"
#435000
b0 +
b0 3
b0 @
b100 ?
17
0)
04
b1 0
b10 >
b1000000 *
b1000000 2
b1000000 D
b100010 %
1"
#440000
0"
#445000
b1 ?
1:
07
b0 /
b0 1
b100011 %
b100 >
b1000000 6
1"
#450000
0"
#455000
b10 ?
14
1)
0:
b0 8
b1 >
b100100 %
1"
#460000
0"
#465000
b10 0
b101 ?
17
0)
04
b100101 %
b10111110 *
b10111110 2
b10111110 D
b10 >
1"
#470000
0"
#475000
b111110 +
b111110 3
b111110 @
b111110 /
b11111110 1
b110 ?
15
1)
07
b10111110 6
b101 >
b100110 %
1"
#480000
0"
#485000
b0 +
b0 3
b0 @
b11 0
b1 ?
19
1=
0)
05
b100111 %
b11111111 *
b11111111 2
b11111111 D
b110 >
1"
#490000
0"
#495000
b1 +
b1 3
b1 @
b10 ?
14
1)
0=
09
b1 8
b1 >
b101000 %
1"
#500000
0"
#505000
b0 +
b0 3
b0 @
b1 0
b100 ?
17
0)
04
b101001 %
b1000000 *
b1000000 2
b1000000 D
b10 >
1"
#510000
0"
#515000
b0 /
b0 1
b1 ?
1:
07
b1000000 6
b100 >
b101010 %
1"
#520000
0"
#525000
b10 ?
14
1)
0:
b101011 %
b1 >
b0 8
1"
#530000
0"
#535000
b101 ?
17
0)
04
b10 0
b10 >
b10111110 *
b10111110 2
b10111110 D
b101100 %
1"
#540000
0"
#545000
b111110 +
b111110 3
b111110 @
b110 ?
15
1)
07
b111110 /
b11111110 1
b101101 %
b101 >
b10111110 6
1"
#550000
0"
#555000
b0 +
b0 3
b0 @
b1 ?
19
1=
0)
05
b11 0
b110 >
b11111111 *
b11111111 2
b11111111 D
b101110 %
1"
#560000
0"
#565000
b1 +
b1 3
b1 @
b10 ?
14
1)
0=
09
b101111 %
b1 >
b1 8
1"
#570000
0"
#575000
b0 +
b0 3
b0 @
b100 ?
17
0)
04
b1 0
b10 >
b1000000 *
b1000000 2
b1000000 D
b110000 %
1"
#580000
0"
#585000
b1 ?
1:
07
b0 /
b0 1
b110001 %
b100 >
b1000000 6
1"
#590000
0"
#595000
b10 ?
14
1)
0:
b0 8
b1 >
b110010 %
1"
#600000
0"
#605000
b10 0
b101 ?
17
0)
04
b110011 %
b10111110 *
b10111110 2
b10111110 D
b10 >
1"
#610000
0"
#615000
b111110 +
b111110 3
b111110 @
b111110 /
b11111110 1
b110 ?
15
1)
07
b10111110 6
b101 >
b110100 %
1"
#620000
0"
#625000
b0 +
b0 3
b0 @
b11 0
b1 ?
19
1=
0)
05
b110101 %
b11111111 *
b11111111 2
b11111111 D
b110 >
1"
#630000
0"
#635000
b1 +
b1 3
b1 @
b10 ?
14
1)
0=
09
b1 8
b1 >
b110110 %
1"
#640000
0"
#645000
b0 +
b0 3
b0 @
b1 0
b100 ?
17
0)
04
b110111 %
b1000000 *
b1000000 2
b1000000 D
b10 >
1"
#650000
0"
#655000
b0 /
b0 1
b1 ?
1:
07
b1000000 6
b100 >
b111000 %
1"
#660000
0"
#665000
b10 ?
14
1)
0:
b111001 %
b1 >
b0 8
1"
#670000
0"
#675000
b101 ?
17
0)
04
b10 0
b10 >
b10111110 *
b10111110 2
b10111110 D
b111010 %
1"
#680000
0"
#685000
b111110 +
b111110 3
b111110 @
b110 ?
15
1)
07
b111110 /
b11111110 1
b111011 %
b101 >
b10111110 6
1"
#690000
0"
#695000
b0 +
b0 3
b0 @
b1 ?
19
1=
0)
05
b11 0
b110 >
b11111111 *
b11111111 2
b11111111 D
b111100 %
1"
#700000
0"
#705000
b1 +
b1 3
b1 @
b10 ?
14
1)
0=
09
b111101 %
b1 >
b1 8
1"
#710000
0"
#715000
b0 +
b0 3
b0 @
b100 ?
17
0)
04
b1 0
b10 >
b1000000 *
b1000000 2
b1000000 D
b111110 %
1"
#720000
0"
#725000
b1 ?
1:
07
b0 /
b0 1
b111111 %
b100 >
b1000000 6
1"
#730000
0"
#735000
b10 ?
14
1)
0:
b0 8
b1 >
b1000000 %
1"
#740000
0"
#745000
b10 0
b101 ?
17
0)
04
b1000001 %
b10111110 *
b10111110 2
b10111110 D
b10 >
1"
#750000
0"
#755000
b111110 +
b111110 3
b111110 @
b111110 /
b11111110 1
b110 ?
15
1)
07
b10111110 6
b101 >
b1000010 %
1"
#760000
0"
#765000
b0 +
b0 3
b0 @
b11 0
b1 ?
19
1=
0)
05
b1000011 %
b11111111 *
b11111111 2
b11111111 D
b110 >
1"
#770000
0"
#775000
b1 +
b1 3
b1 @
b10 ?
14
1)
0=
09
b1 8
b1 >
b1000100 %
1"
#780000
0"
#785000
b0 +
b0 3
b0 @
b1 0
b100 ?
17
0)
04
b1000101 %
b1000000 *
b1000000 2
b1000000 D
b10 >
1"
#790000
0"
#795000
b0 /
b0 1
b1 ?
1:
07
b1000000 6
b100 >
b1000110 %
1"
#800000
0"
#805000
b10 ?
14
1)
0:
b1000111 %
b1 >
b0 8
1"
#810000
0"
#815000
b101 ?
17
0)
04
b10 0
b10 >
b10111110 *
b10111110 2
b10111110 D
b1001000 %
1"
#820000
0"
#825000
b111110 +
b111110 3
b111110 @
b110 ?
15
1)
07
b111110 /
b11111110 1
b1001001 %
b101 >
b10111110 6
1"
#830000
0"
#835000
b0 +
b0 3
b0 @
b1 ?
19
1=
0)
05
b11 0
b110 >
b11111111 *
b11111111 2
b11111111 D
b1001010 %
1"
#840000
0"
#845000
b1 +
b1 3
b1 @
b10 ?
14
1)
0=
09
b1001011 %
b1 >
b1 8
1"
#850000
0"
#855000
b0 +
b0 3
b0 @
b100 ?
17
0)
04
b1 0
b10 >
b1000000 *
b1000000 2
b1000000 D
b1001100 %
1"
#860000
0"
#865000
b1 ?
1:
07
b0 /
b0 1
b1001101 %
b100 >
b1000000 6
1"
#870000
0"
#875000
b10 ?
14
1)
0:
b0 8
b1 >
b1001110 %
1"
#880000
0"
#885000
b10 0
b101 ?
17
0)
04
b1001111 %
b10111110 *
b10111110 2
b10111110 D
b10 >
1"
#890000
0"
#895000
b111110 +
b111110 3
b111110 @
b111110 /
b11111110 1
b110 ?
15
1)
07
b10111110 6
b101 >
b1010000 %
1"
#900000
0"
#905000
b0 +
b0 3
b0 @
b11 0
b1 ?
19
1=
0)
05
b1010001 %
b11111111 *
b11111111 2
b11111111 D
b110 >
1"
#910000
0"
#915000
b1 +
b1 3
b1 @
b10 ?
14
1)
0=
09
b1 8
b1 >
b1010010 %
1"
#920000
0"
#925000
b0 +
b0 3
b0 @
b1 0
b100 ?
17
0)
04
b1010011 %
b1000000 *
b1000000 2
b1000000 D
b10 >
1"
#930000
0"
#935000
b0 /
b0 1
b1 ?
1:
07
b1000000 6
b100 >
b1010100 %
1"
#940000
0"
#945000
b10 ?
14
1)
0:
b1010101 %
b1 >
b0 8
1"
#950000
0"
#955000
b101 ?
17
0)
04
b10 0
b10 >
b10111110 *
b10111110 2
b10111110 D
b1010110 %
1"
#960000
0"
#965000
b111110 +
b111110 3
b111110 @
b110 ?
15
1)
07
b111110 /
b11111110 1
b1010111 %
b101 >
b10111110 6
1"
#970000
0"
#975000
b0 +
b0 3
b0 @
b1 ?
19
1=
0)
05
b11 0
b110 >
b11111111 *
b11111111 2
b11111111 D
b1011000 %
1"
#980000
0"
#985000
b1 +
b1 3
b1 @
b10 ?
14
1)
0=
09
b1011001 %
b1 >
b1 8
1"
#990000
0"
#995000
b0 +
b0 3
b0 @
b100 ?
17
0)
04
b1 0
b10 >
b1000000 *
b1000000 2
b1000000 D
b1011010 %
1"
#1000000
0"
#1005000
b1 ?
1:
07
b0 /
b0 1
b1011011 %
b100 >
b1000000 6
1"
#1010000
0"
#1015000
b10 ?
14
1)
0:
b0 8
b1 >
b1011100 %
1"
#1020000
0"
#1025000
b10 0
b101 ?
17
0)
04
b1011101 %
b10111110 *
b10111110 2
b10111110 D
b10 >
1"
#1030000
0"
#1035000
b111110 +
b111110 3
b111110 @
b111110 /
b11111110 1
b110 ?
15
1)
07
b10111110 6
b101 >
b1011110 %
1"
#1040000
0"
#1045000
b0 +
b0 3
b0 @
b11 0
b1 ?
19
1=
0)
05
b1011111 %
b11111111 *
b11111111 2
b11111111 D
b110 >
1"
#1050000
0"
#1055000
b1 +
b1 3
b1 @
b10 ?
14
1)
0=
09
b1 8
b1 >
b1100000 %
1"
#1060000
0"
#1065000
b0 +
b0 3
b0 @
b1 0
b100 ?
17
0)
04
b1100001 %
b1000000 *
b1000000 2
b1000000 D
b10 >
1"
#1070000
0"
#1075000
b0 /
b0 1
b1 ?
1:
07
b1000000 6
b100 >
b1100010 %
1"
#1080000
0"
#1085000
b10 ?
14
1)
0:
b1100011 %
b1 >
b0 8
1"
#1090000
0"
#1095000
b101 ?
17
0)
04
b10 0
b10 >
b10111110 *
b10111110 2
b10111110 D
b1100100 %
1"
#1100000
0"
#1105000
b111110 +
b111110 3
b111110 @
b110 ?
15
1)
07
b111110 /
b11111110 1
b1100101 %
b101 >
b10111110 6
1"
b0 #
b0 &
b0 A
#1110000
0"
#1115000
b0 +
b0 3
b0 @
b1 ?
19
1=
0)
05
b0 0
b110 >
b0 *
b0 2
b0 D
b1100110 %
1"
#1120000
0"
#1125000
b1 +
b1 3
b1 @
b10 ?
14
1)
0=
09
b1100111 %
b1 >
0.
b0 (
b0 -
b0 B
b0 ;
b1 8
1"
#1130000
0"
#1135000
b0 +
b0 3
b0 @
b100 ?
17
0)
04
b1 0
b10 >
b1000000 *
b1000000 2
b1000000 D
b1101000 %
1"
#1140000
0"
#1145000
b1 ?
19
07
b0 /
b0 1
b1101001 %
b100 >
b1000000 6
1"
#1150000
0"
#1155000
b10 +
b10 3
b10 @
b10 ?
14
1)
09
b10 8
b1 >
b1101010 %
1"
#1160000
0"
#1165000
b0 +
b0 3
b0 @
b10 0
b101 ?
17
0)
04
b1101011 %
b10100001 *
b10100001 2
b10100001 D
b10 >
1"
#1170000
0"
#1175000
b100001 +
b100001 3
b100001 @
b100001 /
b11100001 1
b110 ?
15
1)
07
b10100001 6
b101 >
b1101100 %
1"
#1180000
0"
#1185000
b0 +
b0 3
b0 @
b0 0
b1 ?
19
1=
0)
05
b1101101 %
b1010 *
b1010 2
b1010 D
b110 >
1"
#1190000
0"
#1195000
b11 +
b11 3
b11 @
b10 ?
14
1)
0=
09
b11 8
1.
b1010 (
b1010 -
b1010 B
b1010 ;
b1 >
b1101110 %
1"
#1200000
0"
#1205000
b0 +
b0 3
b0 @
b11 ?
17
0)
04
b1101111 %
b111111 *
b111111 2
b111111 D
b10 >
1"
#1210000
0"
#1215000
b111111 /
b11111111 1
b1 ?
19
1<
07
b111111 6
b11 >
b1110000 %
1"
#1220000
0"
#1225000
b100 +
b100 3
b100 @
b10 ?
14
1)
0<
09
b1110001 %
b1 >
b1001 (
b1001 -
b1001 B
b1001 ;
b100 8
1"
#1230000
0"
#1235000
b0 +
b0 3
b0 @
b100 ?
17
0)
04
b1 0
b10 >
b1000011 *
b1000011 2
b1000011 D
b1110010 %
1"
#1240000
0"
#1245000
b1 ?
1:
07
b11 /
b11 1
b1110011 %
b100 >
b1000011 6
1"
#1250000
0"
#1255000
b11 +
b11 3
b11 @
b10 ?
14
1)
0:
b11 8
b1 >
b1110100 %
1"
#1260000
0"
#1265000
b0 +
b0 3
b0 @
b0 0
b11 ?
17
0)
04
b1110101 %
b111111 *
b111111 2
b111111 D
b10 >
1"
#1270000
0"
#1275000
b111111 /
b11111111 1
b1 ?
19
1<
07
b111111 6
b11 >
b1110110 %
1"
#1280000
0"
#1285000
b100 +
b100 3
b100 @
b10 ?
14
1)
0<
09
b1110111 %
b1 >
b1000 (
b1000 -
b1000 B
b1000 ;
b100 8
1"
#1290000
0"
#1295000
b0 +
b0 3
b0 @
b100 ?
17
0)
04
b1 0
b10 >
b1000011 *
b1000011 2
b1000011 D
b1111000 %
1"
#1300000
0"
#1305000
b1 ?
1:
07
b11 /
b11 1
b1111001 %
b100 >
b1000011 6
1"
#1310000
0"
#1315000
b11 +
b11 3
b11 @
b10 ?
14
1)
0:
b11 8
b1 >
b1111010 %
1"
#1320000
0"
#1325000
b0 +
b0 3
b0 @
b0 0
b11 ?
17
0)
04
b1111011 %
b111111 *
b111111 2
b111111 D
b10 >
1"
#1330000
0"
#1335000
b111111 /
b11111111 1
b1 ?
19
1<
07
b111111 6
b11 >
b1111100 %
1"
#1340000
0"
#1345000
b100 +
b100 3
b100 @
b10 ?
14
1)
0<
09
b1111101 %
b1 >
b111 (
b111 -
b111 B
b111 ;
b100 8
1"
